teledetection/__init__.py
teledetection/cli.py
teledetection/py.typed
teledetection/sdk/__init__.py
teledetection/sdk/http.py
teledetection/sdk/logger.py
teledetection/sdk/model.py
teledetection/sdk/oauth2.py
teledetection/sdk/py.typed
teledetection/sdk/settings.py
teledetection/sdk/signing.py
teledetection/sdk/utils.py
teledetection/upload/__init__.py
teledetection/upload/diff.py
teledetection/upload/py.typed
teledetection/upload/raster.py
teledetection/upload/stac.py
teledetection/upload/transfer.py
teledetection-0.1.7.dist-info/licenses/LICENSE
teledetection-0.1.7.dist-info/METADATA
teledetection-0.1.7.dist-info/WHEEL
teledetection-0.1.7.dist-info/entry_points.txt
teledetection-0.1.7.dist-info/top_level.txt
teledetection-0.1.7.dist-info/RECORD
