Metadata-Version: 2.4
Name: teledetection
Version: 0.1.7
Summary: Software development kit for the Geospatial Data Center of 'la Maison de la Teledetection'
Author-email: Rémi Cresson <remi.cresson@inrae.fr>, Pablo Boizeau <pablo.boizeau@ird.fr>
License: Apache-2.0
Classifier: Programming Language :: Python :: 3.9
Classifier: Programming Language :: Python :: 3.10
Classifier: Programming Language :: Python :: 3.11
Classifier: Topic :: Scientific/Engineering :: GIS
Classifier: Topic :: Scientific/Engineering :: Image Processing
Classifier: License :: OSI Approved :: Apache Software License
Classifier: Operating System :: OS Independent
Requires-Python: >=3.9
License-File: LICENSE
Requires-Dist: setuptools>=61.2
Requires-Dist: click>=7.1
Requires-Dist: pydantic<3.0.0,>=1.7.3
Requires-Dist: pystac>=1.0.0
Requires-Dist: pystac-client>=0.2.0
Requires-Dist: requests>=2.25.1
Requires-Dist: packaging
Requires-Dist: qrcode
Requires-Dist: appdirs
Requires-Dist: pydantic_settings
Provides-Extra: test
Requires-Dist: pytest; extra == "test"
Requires-Dist: coverage; extra == "test"
Provides-Extra: upload
Requires-Dist: rich; extra == "upload"
Requires-Dist: rasterio; extra == "upload"
Requires-Dist: rio-cogeo; extra == "upload"
Requires-Dist: rio-stac; extra == "upload"
Dynamic: license-file
